features_creation/__init__.py
features_creation/features_creation.py
features_creation/transformations/__init__.py
features_creation/transformations/base_transformations.py
features_creation/transformations/bins_transformations.py
features_creation/transformations/cyclical_transformations.py
features_creation/transformations/math_transformations.py
features_creation-0.1.0.dist-info/METADATA
features_creation-0.1.0.dist-info/WHEEL
features_creation-0.1.0.dist-info/RECORD
