Metadata-Version: 2.1
Name: features-creation
Version: 0.1.0
Summary: Creates new DataFrame columns by applying strategically selected operations.
Home-page: https://github.com/andresdigiovanni/features-creation
License: MIT
Author: Andrés Di Giovanni
Author-email: andresdigiovanni@gmail.com
Requires-Python: >=3.9
Classifier: License :: OSI Approved :: MIT License
Classifier: Programming Language :: Python :: 3
Classifier: Programming Language :: Python :: 3.9
Classifier: Programming Language :: Python :: 3.10
Classifier: Programming Language :: Python :: 3.11
Requires-Dist: numpy (>=1.25.1,<2.0.0)
Requires-Dist: pandas (>=2.0.3,<3.0.0)
Requires-Dist: tqdm (>=4.65.0,<5.0.0)
